cloudshell/__init__.py
cloudshell/checkpoint/__init__.py
cloudshell/checkpoint/gaia/__init__.py
cloudshell/checkpoint/gaia/utils.py
cloudshell/checkpoint/gaia/autoload/__init__.py
cloudshell/checkpoint/gaia/autoload/checkpoint_gaia_snmp_autoload.py
cloudshell/checkpoint/gaia/autoload/port_constants.py
cloudshell/checkpoint/gaia/autoload/snmp_if_entity.py
cloudshell/checkpoint/gaia/autoload/snmp_if_port_channel_entity.py
cloudshell/checkpoint/gaia/autoload/snmp_if_port_entity.py
cloudshell/checkpoint/gaia/autoload/snmp_if_table.py
cloudshell/checkpoint/gaia/autoload/snmp_port_attr_tables.py
cloudshell/checkpoint/gaia/cli/__init__.py
cloudshell/checkpoint/gaia/cli/checkpoint_cli_configurator.py
cloudshell/checkpoint/gaia/cli/checkpoint_command_modes.py
cloudshell/checkpoint/gaia/cli/sessions/__init__.py
cloudshell/checkpoint/gaia/cli/sessions/console_ssh_session.py
cloudshell/checkpoint/gaia/cli/sessions/console_telnet_session.py
cloudshell/checkpoint/gaia/command_actions/__init__.py
cloudshell/checkpoint/gaia/command_actions/file_fransfer_actions.py
cloudshell/checkpoint/gaia/command_actions/save_restore_actions.py
cloudshell/checkpoint/gaia/command_actions/snmp_actions.py
cloudshell/checkpoint/gaia/command_actions/system_actions.py
cloudshell/checkpoint/gaia/command_templates/__init__.py
cloudshell/checkpoint/gaia/command_templates/error_map.py
cloudshell/checkpoint/gaia/command_templates/save_restore_templates.py
cloudshell/checkpoint/gaia/command_templates/snmp_configuration_templates.py
cloudshell/checkpoint/gaia/flows/__init__.py
cloudshell/checkpoint/gaia/flows/checkpoint_autoload_flow.py
cloudshell/checkpoint/gaia/flows/checkpoint_configuration_flow.py
cloudshell/checkpoint/gaia/flows/checkpoint_enable_disable_snmp_flow.py
cloudshell/checkpoint/gaia/flows/checkpoint_load_firmware_flow.py
cloudshell/checkpoint/gaia/flows/checkpoint_state_flow.py
cloudshell/checkpoint/gaia/mibs/CHECKPOINT-MIB.py
cloudshell/checkpoint/gaia/mibs/IP-MIB.py
cloudshell_checkpoint-1.0.4.dist-info/METADATA
cloudshell_checkpoint-1.0.4.dist-info/WHEEL
cloudshell_checkpoint-1.0.4.dist-info/top_level.txt
cloudshell_checkpoint-1.0.4.dist-info/RECORD
